fyers_logger.py
otel_fyers_logger-1.0.0.dist-info/METADATA
otel_fyers_logger-1.0.0.dist-info/WHEEL
otel_fyers_logger-1.0.0.dist-info/top_level.txt
otel_fyers_logger-1.0.0.dist-info/RECORD
